docmodel/__init__.py
docmodel/docmodel.py
docmodel/example.py
docmodel/exceptions.py
docmodel/fields.py
docmodel/texttools.py
docmodel/urls.py
docmodel/xpaths.py
docmodel-0.1.0.dist-info/METADATA
docmodel-0.1.0.dist-info/WHEEL
docmodel-0.1.0.dist-info/LICENSE
docmodel-0.1.0.dist-info/RECORD
