Metadata-Version: 2.1
Name: docmodel
Version: 0.1.0
Summary: 
License: MIT
Author: lhaze
Author-email: lhaze@lhaze.name
Requires-Python: >=3.8,<4.0
Classifier: License :: OSI Approved :: MIT License
Classifier: Programming Language :: Python :: 3
Classifier: Programming Language :: Python :: 3.8
Classifier: Programming Language :: Python :: 3.9
Classifier: Programming Language :: Python :: 3.10
Classifier: Programming Language :: Python :: 3.11
Requires-Dist: parsel (>=1.6.0,<2.0.0)
Requires-Dist: pre-commit (>=3.0.4,<4.0.0)
